README.md
setup.py
shary/__init__.py
shary/cli.py
shary/shary.py
shary.egg-info/PKG-INFO
shary.egg-info/SOURCES.txt
shary.egg-info/dependency_links.txt
shary.egg-info/entry_points.txt
shary.egg-info/requires.txt
shary.egg-info/top_level.txt
shary/services/__init__.py
shary/services/anonfiles.py